CHANGES.txt
CONTRIBUTORS.txt
README.txt
TODO.txt
bootstrap.py
buildout.cfg
setup.py
docs/HISTORY.txt
docs/INSTALL.txt
docs/LICENSE.GPL
docs/LICENSE.txt
docs/collector.txt
docs/gmailexport.txt
docs/gmailimport.txt
docs/manifest.txt
docs/manifest_old.txt
src/collective/__init__.py
src/collective.plone.gsxml.egg-info/PKG-INFO
src/collective.plone.gsxml.egg-info/SOURCES.txt
src/collective.plone.gsxml.egg-info/dependency_links.txt
src/collective.plone.gsxml.egg-info/entry_points.txt
src/collective.plone.gsxml.egg-info/namespace_packages.txt
src/collective.plone.gsxml.egg-info/not-zip-safe
src/collective.plone.gsxml.egg-info/requires.txt
src/collective.plone.gsxml.egg-info/top_level.txt
src/collective/plone/__init__.py
src/collective/plone/gsxml/CHANGELOG
src/collective/plone/gsxml/README.rst
src/collective/plone/gsxml/TODO.rst
src/collective/plone/gsxml/__init__.py
src/collective/plone/gsxml/collector.py
src/collective/plone/gsxml/config.py
src/collective/plone/gsxml/configure.zcml
src/collective/plone/gsxml/content.py
src/collective/plone/gsxml/context.py
src/collective/plone/gsxml/events.py
src/collective/plone/gsxml/interfaces.py
src/collective/plone/gsxml/manifest.py
src/collective/plone/gsxml/rootmanifest.py
src/collective/plone/gsxml/utils.py
src/collective/plone/gsxml/version.txt
src/collective/plone/gsxml/browser/__init__.py
src/collective/plone/gsxml/browser/configure.zcml
src/collective/plone/gsxml/browser/gsxml.py
src/collective/plone/gsxml/browser/importexport.py
src/collective/plone/gsxml/browser/images/export_icon.png
src/collective/plone/gsxml/browser/images/import_icon.png
src/collective/plone/gsxml/docs/collector.rst
src/collective/plone/gsxml/docs/fsexport.txt
src/collective/plone/gsxml/docs/fsimport.txt
src/collective/plone/gsxml/profiles/default/actionicons.xml
src/collective/plone/gsxml/profiles/default/actions.xml
src/collective/plone/gsxml/profiles/default/metadata.xml
src/collective/plone/gsxml/tests/__init__.py
src/collective/plone/gsxml/tests/base.py
src/collective/plone/gsxml/tests/test_doctests.py
src/collective/plone/gsxml/tests/test_setup.py