Metadata-Version: 1.0
Name: collective.plone.gsxml
Version: 0.4.7
Summary: A package for importing and exporting content from Plone
Home-page: https://svn.plone.org/svn/collective/gsxml/releases/0.4.7
Author: Stefan Eletzhofer, Ramon Bartl
Author-email: stefan.eletzhofer@inquant.de
License: GPL
Keywords: Plone import export XML
Platform: UNKNOWN
Classifier: Framework :: Zope2
Classifier: Framework :: Zope3
Classifier: Programming Language :: Python
Classifier: Topic :: Software Development :: Libraries :: Python Modules
